ishap/__init__.py
ishap/_utils.py
ishap/explainer.py
ishap/plots.py
ishap-1.0.0.dist-info/licenses/LICENSE
ishap-1.0.0.dist-info/METADATA
ishap-1.0.0.dist-info/WHEEL
ishap-1.0.0.dist-info/top_level.txt
ishap-1.0.0.dist-info/RECORD
