Metadata-Version: 2.4
Name: ishap
Version: 1.0.0
Summary: An implementation of Interaction-aware Shapley Values (ISHAP).
Author-email: Sascha Xu <sascha.xu@yahoo.de>
License: MIT License
Classifier: Programming Language :: Python :: 3
Classifier: License :: OSI Approved :: MIT License
Classifier: Operating System :: OS Independent
Classifier: Intended Audience :: Science/Research
Classifier: Topic :: Scientific/Engineering
Requires-Python: >=3.8
License-File: LICENSE
Requires-Dist: numpy
Requires-Dist: scipy
Requires-Dist: scikit-learn
Requires-Dist: networkx
Requires-Dist: pandas
Requires-Dist: matplotlib
Dynamic: license-file
